which_plates/__init__.py
which_plates/functions.py
which_plates/main.py
which_plates-0.8.0.dist-info/LICENSE
which_plates-0.8.0.dist-info/METADATA
which_plates-0.8.0.dist-info/WHEEL
which_plates-0.8.0.dist-info/RECORD
