Metadata-Version: 2.1
Name: which-plates
Version: 0.8.0
Summary: 
Home-page: https://github.com/iandday/whichPlates
License: GNUv2
Author: Ian Day
Author-email: ian@ianday.me
Requires-Python: >=3.10,<4.0
Classifier: License :: Other/Proprietary License
Classifier: Programming Language :: Python :: 3
Classifier: Programming Language :: Python :: 3.10
Classifier: Programming Language :: Python :: 3.11
Requires-Dist: lxml (>=4.9.2,<5.0.0)
Project-URL: Repository, https://github.com/iandday/whichPlates
